[{"decode":"Bestem ny forventet inntekt","valid":true,"fromDate":-2209078800000,"toDate":null,"code":"BEREGN_FORINT","codeAsString":"BEREGN_FORINT"},{"decode":"Beregn IFU","valid":true,"fromDate":-2209078800000,"toDate":null,"code":"BEREGN_IFU","codeAsString":"BEREGN_IFU"},{"decode":"Beregn UFG","valid":true,"fromDate":-2209078800000,"toDate":null,"code":"BEREGN_UFG","codeAsString":"BEREGN_UFG"},{"decode":"Fastsett UFG","valid":true,"fromDate":-2209078800000,"toDate":null,"code":"FASTSETT_UFG","codeAsString":"FASTSETT_UFG"},{"decode":"Konverter IFU","valid":true,"fromDate":-2209078800000,"toDate":null,"code":"KONVERTER_IFU","codeAsString":"KONVERTER_IFU"}]